[{"movie_id": 9988, "review_id": "5a6940bc9251414a2e009179", "rating": 5.0, "review_text": "Not one of Broken Lizard's strongest entries, but perhaps classic viewing for those in the state that it's characters are: Drunk.\r\n\r\n_Final rating:\u2605\u2605\u00bd - Not quite for me, but I definitely get the appeal._", "created_at": "2018-01-25T02:28:12.494Z"}, {"movie_id": 9988, "review_id": "6449359c2fdec602fca107cb", "rating": 8.0, "review_text": "This was a awesome movie. I love these guys just as good as they were in super troopers. I would definitely like to try this in real life myself sometime. It would be sweet.", "created_at": "2023-04-26T14:30:52.951Z"}]